dstools/__init__.py
dstools/common/__init__.py
dstools/common/aio_utils.py
dstools/common/async_iter_utils.py
dstools/common/dummy_logger.py
dstools/common/io_utils.py
dstools/common/iter_utils.py
dstools/common/json_io.py
dstools/common/time_measure.py
dstools/common/ext/__init__.py
dstools/common/ext/typing_ext.py
dstools/common/image_utils/__init__.py
dstools/common/image_utils/image_io.py
dstools/common/image_utils/image_pixels.py
dstools/common/image_utils/image_validation.py
dstools/compression/__init__.py
dstools/compression/compressor.py
dstools/compression/folder_compress.py
dstools/compression/snappy_compressor.py
dstools/data_manage/__init__.py
dstools/data_manage/data_manager.py
dstools/data_manage/firestore.py
dstools/data_manage/gcs.py
dstools/data_manage/schema.py
dstools/data_manage/collections/__init__.py
dstools/data_manage/collections/db_collection.py
dstools/data_manage/collections/firestore_collection.py
dstools/data_manage/collections/raw_page_collection_with_content.py
dstools/reporting/__init__.py
dstools/reporting/reporter.py
dstools/resource_management/__init__.py
dstools/resource_management/resource.py
dstools/resource_management/resource_config.py
dstools/resource_management/resource_utils.py
dstools/resource_management/resource_storage/__init__.py
dstools/resource_management/resource_storage/resource_downloader.py
dstools/resource_management/resource_storage/resource_uploader.py
dstools/storage/__init__.py
dstools/storage/handlers/__init__.py
dstools/storage/handlers/async_handler.py
dstools/storage/handlers/gcs_handler.py
dstools/storage/handlers/local_handler.py
dstools/storage/handlers/s3_handler.py
dstools/storage/handlers/ssh_handler.py
dstools/storage/handlers/storage_handler.py
dstools/storage/handlers/storage_handler_config.py
python_dstools-0.1.4.dist-info/licenses/LICENSE
python_dstools-0.1.4.dist-info/METADATA
python_dstools-0.1.4.dist-info/WHEEL
python_dstools-0.1.4.dist-info/top_level.txt
python_dstools-0.1.4.dist-info/RECORD
